vxscreenshots-2.6.19.data/scripts/screenshot.sh
vxscreenshots-2.6.19.dist-info/top_level.txt
vxscreenshots-2.6.19.dist-info/METADATA
vxscreenshots-2.6.19.dist-info/DESCRIPTION.rst
vxscreenshots-2.6.19.dist-info/metadata.json
vxscreenshots-2.6.19.dist-info/WHEEL
vxscreenshots-2.6.19.dist-info/entry_points.txt
vxscreenshots-2.6.19.dist-info/RECORD
vxscreenshots/__init__.py
vxscreenshots/icon.svg
vxscreenshots/configure.py
vxscreenshots/vxscreenshots.py
vxscreenshots/config.py
vxscreenshots/watch.py
vxscreenshots/config/autostart/shutter.desktop
vxscreenshots/config/autostart/vxsswatcher.desktop
vxscreenshots/config/autostart/vxssicon.desktop
