Metadata-Version: 2.0
Name: vxscreenshots
Version: 2.6.19
Summary: vxscreenshots: Basic Screenshots manager pushing and sharing automatically to Amazon S3 alá Skitch
Home-page: https://github.com/vauxoo/vxscreenshots
Author: Nhomar Hernández
Author-email: nhomar@vauxoo.com
License: Copyright (c) 2016, Vauxoo OpenSource Specialists
Requires-Dist: boto3
Requires-Dist: botocore
Requires-Dist: watchdog
Requires-Dist: click
